idml2docbook/__init__.py
idml2docbook/__main__.py
idml2docbook/core.py
idml2docbook/idml2hubxml.py
idml2docbook/install_dependencies.py
idml2docbook/map.py
idml2docbook/utils.py
idml2docbook-1.1.4.dist-info/licenses/LICENSE
idml2docbook-1.1.4.dist-info/METADATA
idml2docbook-1.1.4.dist-info/WHEEL
idml2docbook-1.1.4.dist-info/entry_points.txt
idml2docbook-1.1.4.dist-info/top_level.txt
idml2docbook-1.1.4.dist-info/RECORD
