Metadata-Version: 2.4
Name: idml2docbook
Version: 1.1.4
Summary: Convert IDML files to DocBook.
Author-email: Yann Trividic <bonjour@yanntrividic.fr>
License-Expression: GPL-3.0-or-later
Project-URL: Homepage, https://github.com/yanntrividic/idml2docbook
Project-URL: Bug Tracker, https://github.com/yanntrividic/idml2docbook/-/issues
Keywords: idml,docbook,converter
Requires-Python: >=3.8
License-File: LICENSE
Requires-Dist: bs4>=0.0.2
Requires-Dist: lxml>=6.0.0
Requires-Dist: python-dotenv>=1.1.1
Requires-Dist: unidecode>=1.4.0
Requires-Dist: packaging>=25.0
Requires-Dist: natsort>=8.4.0
Requires-Dist: pandas>=2.3.2
Requires-Dist: odfpy>=1.4.1
Dynamic: license-file
